xnode/__init__.py
xnode/xnode.py
xnode/pop/autoctrl.py
xnode/pop/core.py
xnode/pop/ext.py
xnode/pop/tphg.py
xnode-1.4.0.dist-info/LICENSE
xnode-1.4.0.dist-info/METADATA
xnode-1.4.0.dist-info/WHEEL
xnode-1.4.0.dist-info/entry_points.txt
xnode-1.4.0.dist-info/top_level.txt
xnode-1.4.0.dist-info/RECORD
