Metadata-Version: 2.1
Name: xnode
Version: 1.4.0
Summary: This is a CLI management tool for MicroPython-based embedded systems.
Home-page: https://github.com/planxstudio/xkit
Author: chanmin.park
Author-email: devcamp@gmail.com
Keywords: micropython,xnode,genlib
Classifier: Programming Language :: Python :: 3
Classifier: License :: OSI Approved :: MIT License
Classifier: Operating System :: OS Independent
Requires-Python: >=3.8
License-File: LICENSE
Requires-Dist: click
Requires-Dist: python-dotenv
Requires-Dist: pyserial
Requires-Dist: genlib
